{"oldMess":{"channelId":"1166713829481259058","guildId":"1166713491483279414","id":"1168575346073931837","createdTimestamp":1698680473584,"type":0,"system":false,"content":"fa","authorId":"398570545890983937","pinned":false,"tts":false,"nonce":"1168575343011823616","embeds":[],"components":[],"attachments":[],"stickers":[],"position":null,"roleSubscriptionData":null,"editedTimestamp":null,"mentions":{"everyone":false,"users":[],"roles":[],"crosspostedChannels":[],"repliedUser":null,"members":[],"channels":[]},"webhookId":null,"groupActivityApplicationId":null,"applicationId":null,"activity":null,"flags":0,"reference":null,"interaction":null,"cleanContent":"fa"},"newMess":{"channelId":"1166713829481259058","guildId":"1166713491483279414","id":"1168575346073931837","createdTimestamp":1698680473584,"type":0,"system":false,"content":"faty","authorId":"398570545890983937","pinned":false,"tts":false,"nonce":"1168575343011823616","embeds":[],"components":[],"attachments":[],"stickers":[],"position":null,"roleSubscriptionData":null,"editedTimestamp":1698680476233,"mentions":{"everyone":false,"users":[],"roles":[],"crosspostedChannels":[],"repliedUser":null,"members":[],"channels":[]},"webhookId":null,"groupActivityApplicationId":null,"applicationId":null,"activity":null,"flags":0,"reference":null,"interaction":null,"cleanContent":"faty"},"author":{"id":"398570545890983937","bot":false,"system":false,"flags":4194560,"username":"punklorde.mentality","globalName":"Akasha","discriminator":"0","avatar":"b4f4aa05dd09ef2025de991924f6a848","avatarDecoration":null,"createdTimestamp":1515097023223,"defaultAvatarURL":"https://cdn.discordapp.com/embed/avatars/1.png","tag":"punklorde.mentality","avatarURL":"https://cdn.discordapp.com/avatars/398570545890983937/b4f4aa05dd09ef2025de991924f6a848.webp","displayAvatarURL":"https://cdn.discordapp.com/avatars/398570545890983937/b4f4aa05dd09ef2025de991924f6a848.webp"},"channel":"1167585941821599896"}